{"id":21081,"date":"2019-03-13T06:15:50","date_gmt":"2019-03-13T06:15:50","guid":{"rendered":"https:\/\/websitedemos.net\/?post_type=astra-sites&#038;p=21081"},"modified":"2019-07-10T14:14:22","modified_gmt":"2019-07-10T08:44:22","slug":"__trashed-20__trashed","status":"publish","type":"astra-sites","link":"https:\/\/websitedemos.net\/blog\/astra-site\/__trashed-20__trashed\/","title":{"rendered":"Restaurant"},"content":{"rendered":"","protected":false},"author":34,"featured_media":22521,"template":"","astra-site-category":[27],"astra-site-page-builder":[41],"astra-sites-tag":[],"astra-site-type":"premium","required-plugins":[{"slug":"astra-addon","init":"astra-addon\/astra-addon.php","name":"Astra Pro"},{"slug":"brizy","init":"brizy\/brizy.php","name":"Brizy"}],"astra-site-url":"\/\/websitedemos.net\/restaurant-06","astra-site-open-in-new-tab":"0","astra-site-widgets-data":"{\"sidebar-1\":{\"search-2\":{\"title\":\"\"},\"recent-posts-2\":{\"title\":\"\",\"number\":5},\"recent-comments-2\":{\"title\":\"\",\"number\":5},\"archives-2\":{\"title\":\"\",\"count\":0,\"dropdown\":0},\"categories-2\":{\"title\":\"\",\"count\":0,\"hierarchical\":0,\"dropdown\":0},\"meta-2\":{\"title\":\"\"}}}","astra-site-customizer-data":{"astra-settings":{"astra-addon-auto-version":"1.8.7","theme-auto-version":"1.8.7","button-color":"#eb5058","button-h-color":"#000000","button-bg-color":"#f6f3f1","button-bg-h-color":"#f6f3f1","button-radius":0,"button-v-padding":10,"button-h-padding":40,"header-main-rt-section-button-text-color":"","header-main-rt-section-button-text-h-color":"","header-main-rt-section-button-back-color":"","header-main-rt-section-button-back-h-color":"","header-main-rt-section-button-padding":{"desktop":{"top":"","right":"","bottom":"","left":""},"tablet":{"top":"","right":"","bottom":"","left":""},"mobile":{"top":"","right":"","bottom":"","left":""}},"header-main-rt-section-button-border-size":{"top":"","right":"","bottom":"","left":""},"header-main-rt-section-button-border-color":"","header-main-rt-section-button-border-h-color":"","header-main-rt-section-button-border-radius":"","header-main-rt-trans-section-button-text-color":"","header-main-rt-trans-section-button-text-h-color":"","header-main-rt-trans-section-button-back-color":"","header-main-rt-trans-section-button-back-h-color":"","header-main-rt-trans-section-button-padding":"","header-main-rt-trans-section-button-border-size":"","header-main-rt-trans-section-button-border-color":"","header-main-rt-trans-section-button-border-h-color":"","header-main-rt-trans-section-button-border-radius":"","site-content-width":1200,"header-layouts":"header-main-layout-2","disable-primary-nav":false,"header-main-rt-section":"none","header-main-rt-section-button-text":"Button","header-main-rt-section-button-link":"https:\/\/www.wpastra.com","header-main-rt-section-button-style":"theme-button","header-button-style-link":"","header-main-rt-section-html":"<button>+1 910-626-85255<\/button>","header-main-sep":0,"header-main-sep-color":"","header-main-layout-width":"content","primary-submenu-border-divider":"","primary-submenu-border":{"top":"1","bottom":"1","left":"1","right":"1"},"primary-submenu-b-color":"#eaeaea","primary-submenu-item-border":1,"primary-submenu-item-b-color":"#eaeaea","header-main-submenu-container-animation":"","header-main-menu-label-divider":"","mobile-header-breakpoint":"","mobile-header-toggle-target":"icon","header-main-menu-label":"","hide-custom-menu-mobile":1,"header-display-outside-menu":false,"header-main-menu-align":"inline","mobile-header-toggle-btn-style":"fill","mobile-header-toggle-btn-style-color":"#eb5058","mobile-header-toggle-btn-border-radius":"","different-retina-logo":"1","ast-header-retina-logo":"https:\/\/websitedemos.net\/restaurant-06\/wp-content\/uploads\/sites\/352\/2018\/10\/logo-@2x-free-img.png","different-mobile-logo":false,"mobile-header-logo":"","ast-header-responsive-logo-width":{"desktop":"","tablet":"","mobile":"135"},"ast-site-logo-divider":"","display-site-title":false,"display-site-tagline":0,"logo-title-inline":0,"ast-site-icon-divider":"","blog-post-content":"excerpt","blog-post-structure":["image","title-meta"],"blog-meta":["comments","category","author"],"ast-styling-section-blog-width":"","blog-width":"default","blog-max-width":1200,"blog-single-post-structure":["single-image","single-title-meta"],"blog-single-meta":["comments","category","author"],"ast-styling-section-single-blog-layouts":"","blog-single-width":"default","blog-single-max-width":1200,"site-sidebar-layout":"right-sidebar","single-page-sidebar-layout-divider":"","single-page-sidebar-layout":"default","single-post-sidebar-layout":"default","archive-post-sidebar-layout":"default","divider-section-sidebar-width":"","site-sidebar-width":30,"site-sidebar-width-description":"","site-content-layout-divider":"","site-content-layout":"boxed-container","single-page-content-layout":"default","single-post-content-layout":"default","archive-post-content-layout":"default","site-layout-outside-bg-obj":{"background-color":"#f6f3f1","background-image":"","background-repeat":"repeat","background-position":"center center","background-size":"auto","background-attachment":"scroll"},"footer-sml-layout":"footer-sml-layout-2","section-ast-small-footer-layout-info":"","footer-sml-section-1":"custom","footer-sml-section-1-credit":"Copyright \u00a9 [current_year] [site_title] | <a href=\"#\">Credits<\/a>","footer-sml-section-2":"custom","footer-sml-section-2-credit":"Powered by [site_title]","section-ast-small-footer-typography":"","footer-sml-divider":0,"footer-sml-divider-color":"#7a7a7a","footer-layout-width":"content","footer-adv":"disabled","theme-color":"#eb5058","link-color":"#eb5058","text-color":"#000000","link-h-color":"#000000","divider-outside-bg-color":"","footer-color":"#636161","footer-link-color":"#eb5058","footer-link-h-color":"#000000","divider-footer-image":"","footer-bg-obj":{"background-color":"#f6f3f1","background-image":"","background-repeat":"repeat","background-position":"center center","background-size":"auto","background-attachment":"scroll"},"footer-adv-wgt-title-color":"","footer-adv-text-color":"","footer-adv-link-color":"","footer-adv-link-h-color":"","footer-adv-background-divider":"","footer-adv-bg-obj":{"background-color":"","background-image":"","background-repeat":"repeat","background-position":"center center","background-size":"auto","background-attachment":"scroll"},"divider-section-archive-summary-box-typo":"","font-size-archive-summary-title":{"desktop":40,"tablet":"","mobile":"","desktop-unit":"px","tablet-unit":"px","mobile-unit":"px"},"divider-section-archive-typo-archive-title":"","font-size-page-title":{"desktop":30,"tablet":"","mobile":"","desktop-unit":"px","tablet-unit":"px","mobile-unit":"px"},"divider-base-typo":"","body-font-family":"'Playfair Display', serif","body-font-variant":"700","body-font-weight":"700","body-text-transform":"","font-size-body":{"desktop":"16","tablet":"","mobile":"","desktop-unit":"px","tablet-unit":"px","mobile-unit":"px"},"body-line-height":"","para-margin-bottom":"","divider-headings-typo":"","headings-font-family":"'Open Sans Condensed', sans-serif","headings-font-variant":"700","headings-font-weight":"700","headings-text-transform":"none","divider-section-h1":"","font-size-h1":{"desktop":"50","tablet":"43","mobile":"32","desktop-unit":"px","tablet-unit":"px","mobile-unit":"px"},"divider-section-h2":"","font-size-h2":{"desktop":"45","tablet":"35","mobile":"29","desktop-unit":"px","tablet-unit":"px","mobile-unit":"px"},"divider-section-h3":"","font-size-h3":{"desktop":"37","tablet":"33","mobile":"27","desktop-unit":"px","tablet-unit":"px","mobile-unit":"px"},"divider-section-h4":"","font-size-h4":{"desktop":"25","tablet":"","mobile":"","desktop-unit":"px","tablet-unit":"px","mobile-unit":"px"},"divider-section-h5":"","font-size-h5":{"desktop":"18","tablet":"","mobile":"","desktop-unit":"px","tablet-unit":"px","mobile-unit":"px"},"divider-section-h6":"","font-size-h6":{"desktop":"16","tablet":"","mobile":"","desktop-unit":"px","tablet-unit":"px","mobile-unit":"px"},"divider-section-header-typo-title":"","font-size-site-title":{"desktop":35,"tablet":"","mobile":"","desktop-unit":"px","tablet-unit":"px","mobile-unit":"px"},"divider-section-header-typo-tagline":"","font-size-site-tagline":{"desktop":15,"tablet":"","mobile":"","desktop-unit":"px","tablet-unit":"px","mobile-unit":"px"},"divider-section-header-single-title":"","font-size-entry-title":{"desktop":30,"tablet":"","mobile":"","desktop-unit":"px","tablet-unit":"px","mobile-unit":"px"},"transparent-header-bg-color-responsive":{"desktop":"","tablet":"","mobile":""},"transparent-header-color-site-title-responsive":{"desktop":"","tablet":"","mobile":""},"transparent-header-color-h-site-title-responsive":{"desktop":"","tablet":"","mobile":""},"divider-transparent-menu-responsive":"","transparent-menu-bg-color-responsive":{"desktop":"","tablet":"","mobile":""},"transparent-menu-color-responsive":{"desktop":"","tablet":"","mobile":""},"transparent-menu-h-color-responsive":{"desktop":"","tablet":"","mobile":""},"divider-transparent-sub-menu-responsive":"","transparent-submenu-bg-color-responsive":{"desktop":"","tablet":"","mobile":""},"transparent-submenu-color-responsive":{"desktop":"","tablet":"","mobile":""},"transparent-submenu-h-color-responsive":{"desktop":"","tablet":"","mobile":""},"divider-transparent-content-section":"","transparent-content-section-text-color-responsive":{"desktop":"","tablet":"","mobile":""},"transparent-content-section-link-color-responsive":{"desktop":"","tablet":"","mobile":""},"transparent-content-section-link-h-color-responsive":{"desktop":"","tablet":"","mobile":""},"transparent-header-enable":0,"divider-section-transparent-display":"","transparent-header-disable-archive":1,"transparent-header-disable-index":"","transparent-header-disable-page":"","transparent-header-disable-posts":"","transparent-header-on-devices":"both","divider-section-transparent-styling":"","different-transparent-logo":0,"transparent-header-logo":"","different-transparent-retina-logo":false,"transparent-header-retina-logo":"","transparent-header-logo-width":{"desktop":"","tablet":"","mobile":""},"transparent-header-main-sep":0,"transparent-header-main-sep-color":"","scroll-to-top-on-devices":"both","scroll-to-top-icon-position":"right","scroll-to-top-icon-size":"15","scroll-to-top-icon-radius":"","scroll-to-top-icon-color":"","scroll-to-top-icon-bg-color":"","scroll-to-top-icon-h-color":"","scroll-to-top-icon-h-bg-color":"","mobile-menu-style":"fullscreen","flyout-mobile-menu-alignment":"left","mobile-header-menu-all-border":{"top":"","right":"","bottom":"","left":""},"mobile-header-menu-b-color":"#dadada","header-main-rt-section-search-box-type":"slide-search","above-header-section-1-search-box-type":"slide-search","above-header-section-2-search-box-type":"slide-search","below-header-section-1-search-box-type":"slide-search","below-header-section-2-search-box-type":"slide-search","header-custom-layout-above-header":"","header-custom-layout-below-header":"","header-custom-layout-header":"","header-custom-layout-sticky-header":"","header-custom-layout-transparent-header":"","header-custom-color-above-header":"","header-custom-color-primary-header":"","header-custom-color-below-header":"","header-custom-color-transparent-header":"","header-custom-typo-above-header":"","header-custom-typo-primary-header":"","header-custom-typo-below-header":"","header-custom-title_tagline":"","wc-header-cart-header-colors":false,"shop-quick-view-stick-cart":true},"custom-css":".entry-header{\n\tdisplay:none;\n}"},"astra-site-options-data":{"woocommerce_product_attributes":[],"woocommerce_product_cat_list":[],"woocommerce_product_cat":[],"custom_logo":"https:\/\/websitedemos.net\/restaurant-06\/wp-content\/uploads\/sites\/352\/2018\/10\/logo-regular-free-img.png","nav_menu_locations":{"primary":"menu"},"show_on_front":"page","page_on_front":"Home","page_for_posts":"","_fl_builder_enabled_icons":null,"_fl_builder_enabled_modules":null,"_fl_builder_post_types":null,"_fl_builder_color_presets":null,"_fl_builder_services":null,"_fl_builder_settings":null,"_fl_builder_user_access":null,"_fl_builder_enabled_templates":null,"siteorigin_widgets_active":null,"elementor_container_width":null,"elementor_cpt_support":null,"elementor_css_print_method":null,"elementor_default_generic_fonts":null,"elementor_disable_color_schemes":null,"elementor_disable_typography_schemes":null,"elementor_editor_break_lines":null,"elementor_exclude_user_roles":null,"elementor_global_image_lightbox":null,"elementor_page_title_selector":null,"elementor_scheme_color":null,"elementor_scheme_color-picker]":null,"elementor_scheme_typography":null,"elementor_space_between_widgets":null,"elementor_stretched_section_container":null,"woocommerce_shop_page_title":"","woocommerce_cart_page_title":"","woocommerce_checkout_page_title":"","woocommerce_myaccount_page_title":"","woocommerce_edit_address_page_title":"","woocommerce_view_order_page_title":"","woocommerce_change_password_page_title":"","woocommerce_logout_page_title":"","woocommerce_enable_guest_checkout":null,"woocommerce_enable_checkout_login_reminder":null,"woocommerce_enable_signup_and_login_from_checkout":null,"woocommerce_enable_myaccount_registration":null,"woocommerce_registration_generate_username":null,"wpforms_settings":null,"learndash_settings_theme_ld30":null,"learndash_settings_courses_themes":null},"astra-site-wxr-path":"https:\/\/websitedemos.net\/wp-content\/uploads\/astra-sites\/352\/wxr.xml","astra-enabled-extensions":{"advanced-hooks":"advanced-hooks","blog-pro":"","colors-and-background":"","advanced-footer":"","mobile-header":"","header-sections":"","lifterlms":"","learndash":"","advanced-headers":"","site-layouts":"","spacing":"","sticky-header":"","scroll-to-top":"scroll-to-top","transparent-header":"","typography":"","woocommerce":"","edd":"","nav-menu":"","all":"all"},"astra-custom-404":"","featured-image-url":"https:\/\/websitedemos.net\/wp-content\/uploads\/2019\/03\/image-21081-352-resized.jpg","astra-woocommerce-csv-path":"","astra-post-data-mapping":{"astra-advanced-hook":[{"post_id":311,"post_title":"Site footer","mapping":{"ast-advanced-hook-location":{"rule":["basic-global"],"specific":[]}}}],"astra_adv_header":[]},"astra-site-wpforms-path":"https:\/\/websitedemos.net\/wp-content\/uploads\/astra-sites\/352\/wpforms.json","astra-site-taxonomy-mapping":"","astra-site-parent-id":158,"license-status":"valid","request_time":0.6627490520477295,"_links":{"self":[{"href":"https:\/\/websitedemos.net\/wp-json\/wp\/v2\/astra-sites\/21081"}],"collection":[{"href":"https:\/\/websitedemos.net\/wp-json\/wp\/v2\/astra-sites"}],"about":[{"href":"https:\/\/websitedemos.net\/wp-json\/wp\/v2\/types\/astra-sites"}],"author":[{"embeddable":true,"href":"https:\/\/websitedemos.net\/wp-json\/wp\/v2\/users\/34"}],"version-history":[{"count":1,"href":"https:\/\/websitedemos.net\/wp-json\/wp\/v2\/astra-sites\/21081\/revisions"}],"predecessor-version":[{"id":21082,"href":"https:\/\/websitedemos.net\/wp-json\/wp\/v2\/astra-sites\/21081\/revisions\/21082"}],"wp:featuredmedia":[{"embeddable":true,"href":"https:\/\/websitedemos.net\/wp-json\/wp\/v2\/media\/22521"}],"wp:attachment":[{"href":"https:\/\/websitedemos.net\/wp-json\/wp\/v2\/media?parent=21081"}],"wp:term":[{"taxonomy":"astra-site-category","embeddable":true,"href":"https:\/\/websitedemos.net\/wp-json\/wp\/v2\/astra-site-category?post=21081"},{"taxonomy":"astra-site-page-builder","embeddable":true,"href":"https:\/\/websitedemos.net\/wp-json\/wp\/v2\/astra-site-page-builder?post=21081"},{"taxonomy":"astra-sites-tag","embeddable":true,"href":"https:\/\/websitedemos.net\/wp-json\/wp\/v2\/astra-sites-tag?post=21081"}],"curies":[{"name":"wp","href":"https:\/\/api.w.org\/{rel}","templated":true}]}}